src/arb_wave.sv
`default_nettype none
//0x00: clk_div: value for the clock divider
//into it
module arb_wave (
    input wire [3:0] i_param_addr,
    input wire [31:0] i_param_data,
    input wire i_en,
    input wire i_active,
    input wire rst_n,
    input wire clk,

    //BRAM ABSTRACTION
    output logic [ 9:0] o_bram_addr,
    input  wire  [13:0] i_bram_data,

    output logic signed [13:0] o_drive
);

  //param loading

  logic [31:0] clk_div;
  always_ff @(posedge clk, negedge rst_n) begin
    if (!rst_n) begin
      clk_div <= 32'd1;  // default: step every cycle
    end else if (i_en && i_param_addr == 4'd0) begin
      clk_div <= i_param_data;
    end
  end

  logic active_ff;

  always_ff @(posedge clk, negedge rst_n) begin
    if (!rst_n) active_ff <= 1'b0;
    else active_ff <= i_active;
  end
  logic active_pulse;
  assign active_pulse = i_active & ~active_ff;

  //clock divider logic
  logic [31:0] div_counter;
  logic [ 9:0] bram_addr_r;

  always_ff @(posedge clk, negedge rst_n) begin
    if (~rst_n) begin
      div_counter <= 32'b0;
      bram_addr_r <= 10'b0;
    end else if (~i_active) begin
      div_counter <= 32'b0;
      bram_addr_r <= 10'b0;
    end else begin
      if (div_counter == clk_div - 1) begin
        div_counter <= 32'b0;
        if (bram_addr_r != 10'd1023) bram_addr_r <= bram_addr_r + 1;
      end else begin
        div_counter <= div_counter + 1'b1;
      end
    end
  end

  assign o_bram_addr = bram_addr_r;

  //output pipeline stage; accounting for 1 clock cycle BRAM read latency
  //use active_ff (delayed by 1 cycle) so BRAM output is valid before we sample it
  always_ff @(posedge clk, negedge rst_n) begin
    if (~rst_n) o_drive <= 14'b0;
    else if (~active_ff) o_drive <= 14'b0;
    else o_drive <= i_bram_data;
  end


endmodule
`default_nettype wire

verification/tb/tb_arb_wave.sv
`default_nettype none
// ============================================================
// tb_arb_wave.sv — Testbench for arb_wave.sv (Block Type 5)
//
// Uses an inline BRAM model (simple array) to simulate the
// dual-port register file interface exposed by arb_wave.
//
// Compile:
//   iverilog -g2012 -Wall -o sim_awg src/arb_wave.sv verification/tb/tb_arb_wave.sv
//   vvp sim_awg
// Waveform:
//   gtkwave tb_arb_wave.vcd
// ============================================================
module tb_arb_wave;

localparam CLK_HALF = 5;

logic        clk;
logic        rst_n;
logic [3:0]  i_param_addr;
logic [31:0] i_param_data;
logic        i_en;
logic        i_active;

logic [9:0]           o_bram_addr;
logic [13:0]          i_bram_data;
logic signed [13:0]   o_drive;

// ---- DUT ----
arb_wave dut (
    .clk          (clk),
    .rst_n        (rst_n),
    .i_param_addr (i_param_addr),
    .i_param_data (i_param_data),
    .i_en         (i_en),
    .i_active     (i_active),
    .o_bram_addr  (o_bram_addr),
    .i_bram_data  (i_bram_data),
    .o_drive      (o_drive)
);

// ---- Inline BRAM model ----
// Provides synchronous read with 1-cycle latency, like the real BRAM.
// Contents: bram_mem[addr] = addr * 4 (easily verifiable).
logic [13:0] bram_mem [1024];
initial begin
    for (int i = 0; i < 1024; i++)
        bram_mem[i] = 14'(i * 4);
end

// Sync read — model the 1-cycle latency
always_ff @(posedge clk) begin
    i_bram_data <= bram_mem[o_bram_addr];
end

initial clk = 0;
always #CLK_HALF clk = ~clk;

initial begin
    $dumpfile("tb_arb_wave.vcd");
    $dumpvars(0, tb_arb_wave);
end

int pass_count = 0;
int fail_count = 0;

task check14(input string name, input logic [13:0] got, input logic [13:0] expected);
    if (got === expected) begin
        $display("  PASS [%s]: got 0x%04h (%0d)", name, got, got);
        pass_count++;
    end else begin
        $display("  FAIL [%s]: got 0x%04h (%0d), expected 0x%04h (%0d)",
                 name, got, got, expected, expected);
        fail_count++;
    end
endtask

task check10(input string name, input logic [9:0] got, input logic [9:0] expected);
    if (got === expected) begin
        $display("  PASS [%s]: addr=%0d", name, got);
        pass_count++;
    end else begin
        $display("  FAIL [%s]: got addr=%0d, expected %0d", name, got, expected);
        fail_count++;
    end
endtask

task do_reset(input int cycles);
    rst_n <= 0; i_en <= 0; i_active <= 0; i_param_addr <= '0; i_param_data <= '0;
    repeat (cycles) @(negedge clk);
    rst_n <= 1;
    @(negedge clk);
endtask

task load_clk_div(input logic [31:0] div);
    @(negedge clk);
    i_en <= 1; i_param_addr <= 4'd0; i_param_data <= div;
    @(negedge clk);
    i_en <= 0;
endtask

initial begin
    $display("=== tb_arb_wave: begin ===");
    rst_n = 1; i_en = 0; i_active = 0; i_param_addr = '0; i_param_data = '0;

    // ----------------------------------------------------------------
    // TC-A1: Reset — all outputs should be 0
    // ----------------------------------------------------------------
    $display("TC-A1: Reset assertion");
    do_reset(4);
    @(posedge clk); #1;
    check14("TC-A1 o_drive after reset", o_drive, 14'h0);
    check10("TC-A1 o_bram_addr after reset", o_bram_addr, 10'h0);

    // ----------------------------------------------------------------
    // TC-A2: clk_div=1, active → address increments every cycle
    //        o_drive follows bram with 1-cycle latency
    //        bram_mem[n] = n*4, so o_drive[cycle k] = bram_mem[k-1]*4
    // ----------------------------------------------------------------
    $display("TC-A2: clk_div=1, verify address increments and drive output");
    load_clk_div(32'd1);
    @(negedge clk); i_active <= 1;

    // Cycle 0: addr=0, BRAM reads mem[0]=0, but o_drive has 1-cycle latency
    @(posedge clk); #1;
    check10("TC-A2 addr cycle 0", o_bram_addr, 10'd0);

    @(posedge clk); #1;
    check10("TC-A2 addr cycle 1", o_bram_addr, 10'd1);
    check14("TC-A2 o_drive cycle 1 (mem[0]=0)", o_drive, 14'(0 * 4));

    @(posedge clk); #1;
    check10("TC-A2 addr cycle 2", o_bram_addr, 10'd2);
    check14("TC-A2 o_drive cycle 2 (mem[1]=4)", o_drive, 14'(1 * 4));

    @(posedge clk); #1;
    check10("TC-A2 addr cycle 3", o_bram_addr, 10'd3);
    check14("TC-A2 o_drive cycle 3 (mem[2]=8)", o_drive, 14'(2 * 4));

    @(negedge clk); i_active <= 0;

    // ----------------------------------------------------------------
    // TC-A3: clk_div=4 — address advances every 4 cycles
    // ----------------------------------------------------------------
    $display("TC-A3: clk_div=4, address advances every 4 cycles");
    do_reset(2);
    load_clk_div(32'd4);
    @(negedge clk); i_active <= 1;
    // Run 16 cycles — addr should advance 4 times (0→1→2→3→4)
    repeat (4) @(posedge clk);
    @(posedge clk); #1;
    check10("TC-A3 addr after 4 div-cycles", o_bram_addr, 10'd1);  // 4 cycles at div=4 = 1 advance
    repeat (4) @(posedge clk);
    @(posedge clk); #1;
    check10("TC-A3 addr after 8 div-cycles", o_bram_addr, 10'd2);
    @(negedge clk); i_active <= 0;

    // ----------------------------------------------------------------
    // TC-A4: Deassert active → o_drive=0, addr resets to 0
    // ----------------------------------------------------------------
    $display("TC-A4: Deassert active resets addr and clears output");
    do_reset(2);
    load_clk_div(32'd1);
    @(negedge clk); i_active <= 1;
    repeat (10) @(posedge clk);  // advance addr to ~10
    @(negedge clk); i_active <= 0;
    @(posedge clk); #1;
    check14("TC-A4 o_drive=0 after deassert", o_drive, 14'h0);
    check10("TC-A4 addr reset to 0", o_bram_addr, 10'd0);

    // ----------------------------------------------------------------
    // TC-A5: Address saturation at 1023 (does NOT wrap)
    // ----------------------------------------------------------------
    $display("TC-A5: Address saturates at 1023");
    do_reset(2);
    load_clk_div(32'd1);
    @(negedge clk); i_active <= 1;
    // Advance to addr 1023
    repeat (1023) @(posedge clk);
    @(posedge clk); #1;
    check10("TC-A5 addr at 1023", o_bram_addr, 10'd1023);
    // Extra cycles — should stay at 1023
    repeat (5) @(posedge clk);
    @(posedge clk); #1;
    check10("TC-A5 addr stays at 1023 (no wrap)", o_bram_addr, 10'd1023);
    @(negedge clk); i_active <= 0;

    // ----------------------------------------------------------------
    // TC-A6: clk_div=0 edge case (div_counter == 0-1 = all-ones)
    //        addr should never advance since counter never reaches clk_div-1 = 0xFFFFFFFF
    // ----------------------------------------------------------------
    $display("TC-A6: clk_div=0 edge case (addr stuck at 0)");
    do_reset(2);
    load_clk_div(32'd0);
    @(negedge clk); i_active <= 1;
    repeat (10) @(posedge clk);
    @(posedge clk); #1;
    check10("TC-A6 addr stuck at 0 when clk_div=0", o_bram_addr, 10'd0);
    @(negedge clk); i_active <= 0;

    // ----------------------------------------------------------------
    // TC-A7: Default clk_div=1 after reset (no explicit load)
    // ----------------------------------------------------------------
    $display("TC-A7: Default clk_div=1 after reset (advances every cycle)");
    do_reset(2);
    @(negedge clk); i_active <= 1;
    @(posedge clk); #1;
    check10("TC-A7 addr cycle 1", o_bram_addr, 10'd0);  // cycle 0 still addr=0
    @(posedge clk); #1;
    check10("TC-A7 addr cycle 2 = 1", o_bram_addr, 10'd1);
    @(negedge clk); i_active <= 0;

    // ----------------------------------------------------------------
    // TC-A8: active_pulse dead code — verify no spurious glitches
    //        (active_ff and active_pulse exist but are unused)
    // ----------------------------------------------------------------
    $display("TC-A8: active_pulse (dead code) — no glitch on first active cycle");
    do_reset(2);
    load_clk_div(32'd1);
    @(negedge clk); i_active <= 1;
    @(posedge clk); #1;
    // addr should be 0 (first cycle), not jump to 1 from a spurious active_pulse effect
    check10("TC-A8 no addr jump on first cycle", o_bram_addr, 10'd0);
    @(negedge clk); i_active <= 0;

    $display("=== tb_arb_wave: %0d passed, %0d failed ===", pass_count, fail_count);
    if (fail_count == 0)
        $display("PASS: arb_wave block");
    else
        $fatal(1, "FAIL: arb_wave block has %0d failures", fail_count);

    $finish;
end

// Timeout — TC-A5 runs 1023+ cycles so needs generous budget
initial begin
    #500000;
    $fatal(1, "TIMEOUT: tb_arb_wave exceeded 500000 time units");
end

endmodule
`default_nettype wire

verification/tb/tb_arb_wave.vcd
$date
	Tue Apr  7 12:08:40 2026
$end
$version
	ModelSim Version 2020.1
$end
$timescale
	1ps
$end

$scope module tb_arb_wave $end
$var parameter 32 ! CLK_HALF $end
$var reg 1 " clk $end
$var reg 1 # rst_n $end
$var reg 4 $ i_param_addr [3:0] $end
$var reg 32 % i_param_data [31:0] $end
$var reg 1 & i_en $end
$var reg 1 ' i_active $end
$var reg 10 ( o_bram_addr [9:0] $end
$var reg 14 ) i_bram_data [13:0] $end
$var reg 14 * o_drive [13:0] $end
$var integer 32 + pass_count $end
$var integer 32 , fail_count $end

$scope task check14 $end
$var reg 14 - got [13:0] $end
$var reg 14 . expected [13:0] $end
$upscope $end

$scope task check10 $end
$var reg 10 / got [9:0] $end
$var reg 10 0 expected [9:0] $end
$upscope $end

$scope task do_reset $end
$var integer 32 1 cycles $end
$upscope $end

$scope task load_clk_div $end
$var reg 32 2 div [31:0] $end
$upscope $end

$scope module dut $end
$var wire 1 3 i_param_addr [3] $end
$var wire 1 4 i_param_addr [2] $end
$var wire 1 5 i_param_addr [1] $end
$var wire 1 6 i_param_addr [0] $end
$var wire 1 7 i_param_data [31] $end
$var wire 1 8 i_param_data [30] $end
$var wire 1 9 i_param_data [29] $end
$var wire 1 : i_param_data [28] $end
$var wire 1 ; i_param_data [27] $end
$var wire 1 < i_param_data [26] $end
$var wire 1 = i_param_data [25] $end
$var wire 1 > i_param_data [24] $end
$var wire 1 ? i_param_data [23] $end
$var wire 1 @ i_param_data [22] $end
$var wire 1 A i_param_data [21] $end
$var wire 1 B i_param_data [20] $end
$var wire 1 C i_param_data [19] $end
$var wire 1 D i_param_data [18] $end
$var wire 1 E i_param_data [17] $end
$var wire 1 F i_param_data [16] $end
$var wire 1 G i_param_data [15] $end
$var wire 1 H i_param_data [14] $end
$var wire 1 I i_param_data [13] $end
$var wire 1 J i_param_data [12] $end
$var wire 1 K i_param_data [11] $end
$var wire 1 L i_param_data [10] $end
$var wire 1 M i_param_data [9] $end
$var wire 1 N i_param_data [8] $end
$var wire 1 O i_param_data [7] $end
$var wire 1 P i_param_data [6] $end
$var wire 1 Q i_param_data [5] $end
$var wire 1 R i_param_data [4] $end
$var wire 1 S i_param_data [3] $end
$var wire 1 T i_param_data [2] $end
$var wire 1 U i_param_data [1] $end
$var wire 1 V i_param_data [0] $end
$var wire 1 W i_en $end
$var wire 1 X i_active $end
$var wire 1 Y rst_n $end
$var wire 1 Z clk $end
$var reg 10 [ o_bram_addr [9:0] $end
$var wire 1 \ i_bram_data [13] $end
$var wire 1 ] i_bram_data [12] $end
$var wire 1 ^ i_bram_data [11] $end
$var wire 1 _ i_bram_data [10] $end
$var wire 1 ` i_bram_data [9] $end
$var wire 1 a i_bram_data [8] $end
$var wire 1 b i_bram_data [7] $end
$var wire 1 c i_bram_data [6] $end
$var wire 1 d i_bram_data [5] $end
$var wire 1 e i_bram_data [4] $end
$var wire 1 f i_bram_data [3] $end
$var wire 1 g i_bram_data [2] $end
$var wire 1 h i_bram_data [1] $end
$var wire 1 i i_bram_data [0] $end
$var reg 14 j o_drive [13:0] $end
$var reg 32 k clk_div [31:0] $end
$var reg 1 l active_ff $end
$var reg 1 m active_pulse $end
$var reg 32 n div_counter [31:0] $end
$var reg 10 o bram_addr_r [9:0] $end
$upscope $end
$upscope $end
$enddefinitions $end
#0
$dumpvars
0"
0#
b0 $
b0 %
0&
0'
b0 (
bx )
b0 *
b0 [
b0 j
b1 k
0l
0m
b0 n
b0 o
bx -
bx .
bx /
bx 0
bx 2
b101 !
b0 +
b0 ,
b100 1
0Z
0Y
06
05
04
03
0V
0U
0T
0S
0R
0Q
0P
0O
0N
0M
0L
0K
0J
0I
0H
0G
0F
0E
0D
0C
0B
0A
0@
0?
0>
0=
0<
0;
0:
09
08
07
0W
0X
xi
xh
xg
xf
xe
xd
xc
xb
xa
x`
x_
x^
x]
x\
$end
#5
1"
1Z
b0 )
0i
0h
0g
0f
0e
0d
0c
0b
0a
0`
0_
0^
0]
0\
#10
0"
0Z
#15
1"
1Z
#20
0"
0Z
#25
1"
1Z
#30
0"
0Z
#35
1"
1Z
#40
0"
0Z
1#
1Y
#45
1"
1Z
#50
0"
0Z
#55
1"
1Z
#56
b0 -
b0 .
b1 +
b0 /
b0 0
b10 +
b1 2
#60
0"
0Z
1&
b1 %
1W
1V
#65
1"
1Z
#70
0"
0Z
0&
0W
#75
1"
1Z
#80
0"
0Z
1'
1X
1m
#85
1"
1Z
1l
b1 o
b1 [
0m
b1 (
#86
b1 /
b1 ,
#90
0"
0Z
#95
1"
1Z
b10 o
b100 )
b10 [
1g
b10 (
#96
b10 /
b1 0
b10 ,
b11 +
#100
0"
0Z
#105
1"
1Z
b11 o
b100 j
b1000 )
b100 *
b11 [
0g
1f
b11 (
#106
b11 /
b10 0
b11 ,
b100 -
b100 .
b100 +
#110
0"
0Z
#115
1"
1Z
b100 o
b1000 j
b1100 )
b1000 *
b100 [
1g
b100 (
#116
b100 /
b11 0
b100 ,
b1000 -
b1000 .
b101 +
#120
0"
0Z
b10 1
0'
0#
b0 %
0X
0V
0Y
0l
b0 o
b0 j
b0 *
b0 [
b0 (
#125
1"
1Z
b0 )
0g
0f
#130
0"
0Z
#135
1"
1Z
#140
0"
0Z
1#
1Y
#145
1"
1Z
#150
0"
0Z
b100 2
#155
1"
1Z
#160
0"
0Z
1&
b100 %
1W
1T
#165
1"
1Z
b100 k
#170
0"
0Z
0&
0W
#175
1"
1Z
#180
0"
0Z
1'
1X
1m
#185
1"
1Z
1l
b1 n
0m
#190
0"
0Z
#195
1"
1Z
b10 n
#200
0"
0Z
#205
1"
1Z
b11 n
#210
0"
0Z
#215
1"
1Z
b0 n
b1 o
b1 [
b1 (
#220
0"
0Z
#225
1"
1Z
b1 n
b100 )
1g
#226
b1 /
b1 0
b110 +
#230
0"
0Z
#235
1"
1Z
b10 n
b100 j
b100 *
#240
0"
0Z
#245
1"
1Z
b11 n
#250
0"
0Z
#255
1"
1Z
b0 n
b10 o
b10 [
b10 (
#260
0"
0Z
#265
1"
1Z
b1 n
b1000 )
0g
1f
#270
0"
0Z
#275
1"
1Z
b10 n
b1000 j
b1000 *
#276
b10 /
b10 0
b111 +
#280
0"
0Z
0'
0#
b0 %
0X
0T
0Y
b1 k
0l
b0 n
b0 o
b0 j
b0 *
b0 [
b0 (
#285
1"
1Z
b0 )
0f
#290
0"
0Z
#295
1"
1Z
#300
0"
0Z
1#
1Y
#305
1"
1Z
#310
0"
0Z
b1 2
#315
1"
1Z
#320
0"
0Z
1&
b1 %
1W
1V
#325
1"
1Z
#330
0"
0Z
0&
0W
#335
1"
1Z
#340
0"
0Z
1'
1X
1m
#345
1"
1Z
1l
b1 o
b1 [
0m
b1 (
#350
0"
0Z
#355
1"
1Z
b10 o
b100 )
b10 [
1g
b10 (
#360
0"
0Z
#365
1"
1Z
b11 o
b100 j
b1000 )
b100 *
b11 [
0g
1f
b11 (
#370
0"
0Z
#375
1"
1Z
b100 o
b1000 j
b1100 )
b1000 *
b100 [
1g
b100 (
#380
0"
0Z
#385
1"
1Z
b101 o
b1100 j
b10000 )
b1100 *
b101 [
0g
0f
1e
b101 (
#390
0"
0Z
#395
1"
1Z
b110 o
b10000 j
b10100 )
b10000 *
b110 [
1g
b110 (
#400
0"
0Z
#405
1"
1Z
b111 o
b10100 j
b11000 )
b10100 *
b111 [
0g
1f
b111 (
#410
0"
0Z
#415
1"
1Z
b1000 o
b11000 j
b11100 )
b11000 *
b1000 [
1g
b1000 (
#420
0"
0Z
#425
1"
1Z
b1001 o
b11100 j
b100000 )
b11100 *
b1001 [
0g
0f
0e
1d
b1001 (
#430
0"
0Z
#435
1"
1Z
b1010 o
b100000 j
b100100 )
b100000 *
b1010 [
1g
b1010 (
#440
0"
0Z
0'
0X
#445
1"
1Z
0l
b0 o
b0 j
b101000 )
b0 *
b0 [
0g
1f
b0 (
#446
b0 -
b0 .
b1000 +
b0 /
b0 0
b1001 +
0#
b0 %
0V
0Y
#450
0"
0Z
#455
1"
1Z
b0 )
0f
0d
#460
0"
0Z
1#
1Y
#465
1"
1Z
#470
0"
0Z
#475
1"
1Z
#480
0"
0Z
1&
b1 %
1W
1V
#485
1"
1Z
#490
0"
0Z
0&
0W
#495
1"
1Z
#500
0"
0Z
1'
1X
1m
#505
1"
1Z
1l
b1 o
b1 [
0m
b1 (
#510
0"
0Z
#515
1"
1Z
b10 o
b100 )
b10 [
1g
b10 (
#520
0"
0Z
#525
1"
1Z
b11 o
b100 j
b1000 )
b100 *
b11 [
0g
1f
b11 (
#530
0"
0Z
#535
1"
1Z
b100 o
b1000 j
b1100 )
b1000 *
b100 [
1g
b100 (
#540
0"
0Z
#545
1"
1Z
b101 o
b1100 j
b10000 )
b1100 *
b101 [
0g
0f
1e
b101 (
#550
0"
0Z
#555
1"
1Z
b110 o
b10000 j
b10100 )
b10000 *
b110 [
1g
b110 (
#560
0"
0Z
#565
1"
1Z
b111 o
b10100 j
b11000 )
b10100 *
b111 [
0g
1f
b111 (
#570
0"
0Z
#575
1"
1Z
b1000 o
b11000 j
b11100 )
b11000 *
b1000 [
1g
b1000 (
#580
0"
0Z
#585
1"
1Z
b1001 o
b11100 j
b100000 )
b11100 *
b1001 [
0g
0f
0e
1d
b1001 (
#590
0"
0Z
#595
1"
1Z
b1010 o
b100000 j
b100100 )
b100000 *
b1010 [
1g
b1010 (
#600
0"
0Z
#605
1"
1Z
b1011 o
b100100 j
b101000 )
b100100 *
b1011 [
0g
1f
b1011 (
#610
0"
0Z
#615
1"
1Z
b1100 o
b101000 j
b101100 )
b101000 *
b1100 [
1g
b1100 (
#620
0"
0Z
#625
1"
1Z
b1101 o
b101100 j
b110000 )
b101100 *
b1101 [
0g
0f
1e
b1101 (
#630
0"
0Z
#635
1"
1Z
b1110 o
b110000 j
b110100 )
b110000 *
b1110 [
1g
b1110 (
#640
0"
0Z
#645
1"
1Z
b1111 o
b110100 j
b111000 )
b110100 *
b1111 [
0g
1f
b1111 (
#650
0"
0Z
#655
1"
1Z
b10000 o
b111000 j
b111100 )
b111000 *
b10000 [
1g
b10000 (
#660
0"
0Z
#665
1"
1Z
b10001 o
b111100 j
b1000000 )
b111100 *
b10001 [
0g
0f
0e
0d
1c
b10001 (
#670
0"
0Z
#675
1"
1Z
b10010 o
b1000000 j
b1000100 )
b1000000 *
b10010 [
1g
b10010 (
#680
0"
0Z
#685
1"
1Z
b10011 o
b1000100 j
b1001000 )
b1000100 *
b10011 [
0g
1f
b10011 (
#690
0"
0Z
#695
1"
1Z
b10100 o
b1001000 j
b1001100 )
b1001000 *
b10100 [
1g
b10100 (
#700
0"
0Z
#705
1"
1Z
b10101 o
b1001100 j
b1010000 )
b1001100 *
b10101 [
0g
0f
1e
b10101 (
#710
0"
0Z
#715
1"
1Z
b10110 o
b1010000 j
b1010100 )
b1010000 *
b10110 [
1g
b10110 (
#720
0"
0Z
#725
1"
1Z
b10111 o
b1010100 j
b1011000 )
b1010100 *
b10111 [
0g
1f
b10111 (
#730
0"
0Z
#735
1"
1Z
b11000 o
b1011000 j
b1011100 )
b1011000 *
b11000 [
1g
b11000 (
#740
0"
0Z
#745
1"
1Z
b11001 o
b1011100 j
b1100000 )
b1011100 *
b11001 [
0g
0f
0e
1d
b11001 (
#750
0"
0Z
#755
1"
1Z
b11010 o
b1100000 j
b1100100 )
b1100000 *
b11010 [
1g
b11010 (
#760
0"
0Z
#765
1"
1Z
b11011 o
b1100100 j
b1101000 )
b1100100 *
b11011 [
0g
1f
b11011 (
#770
0"
0Z
#775
1"
1Z
b11100 o
b1101000 j
b1101100 )
b1101000 *
b11100 [
1g
b11100 (
#780
0"
0Z
#785
1"
1Z
b11101 o
b1101100 j
b1110000 )
b1101100 *
b11101 [
0g
0f
1e
b11101 (
#790
0"
0Z
#795
1"
1Z
b11110 o
b1110000 j
b1110100 )
b1110000 *
b11110 [
1g
b11110 (
#800
0"
0Z
#805
1"
1Z
b11111 o
b1110100 j
b1111000 )
b1110100 *
b11111 [
0g
1f
b11111 (
#810
0"
0Z
#815
1"
1Z
b100000 o
b1111000 j
b1111100 )
b1111000 *
b100000 [
1g
b100000 (
#820
0"
0Z
#825
1"
1Z
b100001 o
b1111100 j
b10000000 )
b1111100 *
b100001 [
0g
0f
0e
0d
0c
1b
b100001 (
#830
0"
0Z
#835
1"
1Z
b100010 o
b10000000 j
b10000100 )
b10000000 *
b100010 [
1g
b100010 (
#840
0"
0Z
#845
1"
1Z
b100011 o
b10000100 j
b10001000 )
b10000100 *
b100011 [
0g
1f
b100011 (
#850
0"
0Z
#855
1"
1Z
b100100 o
b10001000 j
b10001100 )
b10001000 *
b100100 [
1g
b100100 (
#860
0"
0Z
#865
1"
1Z
b100101 o
b10001100 j
b10010000 )
b10001100 *
b100101 [
0g
0f
1e
b100101 (
#870
0"
0Z
#875
1"
1Z
b100110 o
b10010000 j
b10010100 )
b10010000 *
b100110 [
1g
b100110 (
#880
0"
0Z
#885
1"
1Z
b100111 o
b10010100 j
b10011000 )
b10010100 *
b100111 [
0g
1f
b100111 (
#890
0"
0Z
#895
1"
1Z
b101000 o
b10011000 j
b10011100 )
b10011000 *
b101000 [
1g
b101000 (
#900
0"
0Z
#905
1"
1Z
b101001 o
b10011100 j
b10100000 )
b10011100 *
b101001 [
0g
0f
0e
1d
b101001 (
#910
0"
0Z
#915
1"
1Z
b101010 o
b10100000 j
b10100100 )
b10100000 *
b101010 [
1g
b101010 (
#920
0"
0Z
#925
1"
1Z
b101011 o
b10100100 j
b10101000 )
b10100100 *
b101011 [
0g
1f
b101011 (
#930
0"
0Z
#935
1"
1Z
b101100 o
b10101000 j
b10101100 )
b10101000 *
b101100 [
1g
b101100 (
#940
0"
0Z
#945
1"
1Z
b101101 o
b10101100 j
b10110000 )
b10101100 *
b101101 [
0g
0f
1e
b101101 (
#950
0"
0Z
#955
1"
1Z
b101110 o
b10110000 j
b10110100 )
b10110000 *
b101110 [
1g
b101110 (
#960
0"
0Z
#965
1"
1Z
b101111 o
b10110100 j
b10111000 )
b10110100 *
b101111 [
0g
1f
b101111 (
#970
0"
0Z
#975
1"
1Z
b110000 o
b10111000 j
b10111100 )
b10111000 *
b110000 [
1g
b110000 (
#980
0"
0Z
#985
1"
1Z
b110001 o
b10111100 j
b11000000 )
b10111100 *
b110001 [
0g
0f
0e
0d
1c
b110001 (
#990
0"
0Z
#995
1"
1Z
b110010 o
b11000000 j
b11000100 )
b11000000 *
b110010 [
1g
b110010 (
#1000
0"
0Z
#1005
1"
1Z
b110011 o
b11000100 j
b11001000 )
b11000100 *
b110011 [
0g
1f
b110011 (
#1010
0"
0Z
#1015
1"
1Z
b110100 o
b11001000 j
b11001100 )
b11001000 *
b110100 [
1g
b110100 (
#1020
0"
0Z
#1025
1"
1Z
b110101 o
b11001100 j
b11010000 )
b11001100 *
b110101 [
0g
0f
1e
b110101 (
#1030
0"
0Z
#1035
1"
1Z
b110110 o
b11010000 j
b11010100 )
b11010000 *
b110110 [
1g
b110110 (
#1040
0"
0Z
#1045
1"
1Z
b110111 o
b11010100 j
b11011000 )
b11010100 *
b110111 [
0g
1f
b110111 (
#1050
0"
0Z
#1055
1"
1Z
b111000 o
b11011000 j
b11011100 )
b11011000 *
b111000 [
1g
b111000 (
#1060
0"
0Z
#1065
1"
1Z
b111001 o
b11011100 j
b11100000 )
b11011100 *
b111001 [
0g
0f
0e
1d
b111001 (
#1070
0"
0Z
#1075
1"
1Z
b111010 o
b11100000 j
b11100100 )
b11100000 *
b111010 [
1g
b111010 (
#1080
0"
0Z
#1085
1"
1Z
b111011 o
b11100100 j
b11101000 )
b11100100 *
b111011 [
0g
1f
b111011 (
#1090
0"
0Z
#1095
1"
1Z
b111100 o
b11101000 j
b11101100 )
b11101000 *
b111100 [
1g
b111100 (
#1100
0"
0Z
#1105
1"
1Z
b111101 o
b11101100 j
b11110000 )
b11101100 *
b111101 [
0g
0f
1e
b111101 (
#1110
0"
0Z
#1115
1"
1Z
b111110 o
b11110000 j
b11110100 )
b11110000 *
b111110 [
1g
b111110 (
#1120
0"
0Z
#1125
1"
1Z
b111111 o
b11110100 j
b11111000 )
b11110100 *
b111111 [
0g
1f
b111111 (
#1130
0"
0Z
#1135
1"
1Z
b1000000 o
b11111000 j
b11111100 )
b11111000 *
b1000000 [
1g
b1000000 (
#1140
0"
0Z
#1145
1"
1Z
b1000001 o
b11111100 j
b100000000 )
b11111100 *
b1000001 [
0g
0f
0e
0d
0c
0b
1a
b1000001 (
#1150
0"
0Z
#1155
1"
1Z
b1000010 o
b100000000 j
b100000100 )
b100000000 *
b1000010 [
1g
b1000010 (
#1160
0"
0Z
#1165
1"
1Z
b1000011 o
b100000100 j
b100001000 )
b100000100 *
b1000011 [
0g
1f
b1000011 (
#1170
0"
0Z
#1175
1"
1Z
b1000100 o
b100001000 j
b100001100 )
b100001000 *
b1000100 [
1g
b1000100 (
#1180
0"
0Z
#1185
1"
1Z
b1000101 o
b100001100 j
b100010000 )
b100001100 *
b1000101 [
0g
0f
1e
b1000101 (
#1190
0"
0Z
#1195
1"
1Z
b1000110 o
b100010000 j
b100010100 )
b100010000 *
b1000110 [
1g
b1000110 (
#1200
0"
0Z
#1205
1"
1Z
b1000111 o
b100010100 j
b100011000 )
b100010100 *
b1000111 [
0g
1f
b1000111 (
#1210
0"
0Z
#1215
1"
1Z
b1001000 o
b100011000 j
b100011100 )
b100011000 *
b1001000 [
1g
b1001000 (
#1220
0"
0Z
#1225
1"
1Z
b1001001 o
b100011100 j
b100100000 )
b100011100 *
b1001001 [
0g
0f
0e
1d
b1001001 (
#1230
0"
0Z
#1235
1"
1Z
b1001010 o
b100100000 j
b100100100 )
b100100000 *
b1001010 [
1g
b1001010 (
#1240
0"
0Z
#1245
1"
1Z
b1001011 o
b100100100 j
b100101000 )
b100100100 *
b1001011 [
0g
1f
b1001011 (
#1250
0"
0Z
#1255
1"
1Z
b1001100 o
b100101000 j
b100101100 )
b100101000 *
b1001100 [
1g
b1001100 (
#1260
0"
0Z
#1265
1"
1Z
b1001101 o
b100101100 j
b100110000 )
b100101100 *
b1001101 [
0g
0f
1e
b1001101 (
#1270
0"
0Z
#1275
1"
1Z
b1001110 o
b100110000 j
b100110100 )
b100110000 *
b1001110 [
1g
b1001110 (
#1280
0"
0Z
#1285
1"
1Z
b1001111 o
b100110100 j
b100111000 )
b100110100 *
b1001111 [
0g
1f
b1001111 (
#1290
0"
0Z
#1295
1"
1Z
b1010000 o
b100111000 j
b100111100 )
b100111000 *
b1010000 [
1g
b1010000 (
#1300
0"
0Z
#1305
1"
1Z
b1010001 o
b100111100 j
b101000000 )
b100111100 *
b1010001 [
0g
0f
0e
0d
1c
b1010001 (
#1310
0"
0Z
#1315
1"
1Z
b1010010 o
b101000000 j
b101000100 )
b101000000 *
b1010010 [
1g
b1010010 (
#1320
0"
0Z
#1325
1"
1Z
b1010011 o
b101000100 j
b101001000 )
b101000100 *
b1010011 [
0g
1f
b1010011 (
#1330
0"
0Z
#1335
1"
1Z
b1010100 o
b101001000 j
b101001100 )
b101001000 *
b1010100 [
1g
b1010100 (
#1340
0"
0Z
#1345
1"
1Z
b1010101 o
b101001100 j
b101010000 )
b101001100 *
b1010101 [
0g
0f
1e
b1010101 (
#1350
0"
0Z
#1355
1"
1Z
b1010110 o
b101010000 j
b101010100 )
b101010000 *
b1010110 [
1g
b1010110 (
#1360
0"
0Z
#1365
1"
1Z
b1010111 o
b101010100 j
b101011000 )
b101010100 *
b1010111 [
0g
1f
b1010111 (
#1370
0"
0Z
#1375
1"
1Z
b1011000 o
b101011000 j
b101011100 )
b101011000 *
b1011000 [
1g
b1011000 (
#1380
0"
0Z
#1385
1"
1Z
b1011001 o
b101011100 j
b101100000 )
b101011100 *
b1011001 [
0g
0f
0e
1d
b1011001 (
#1390
0"
0Z
#1395
1"
1Z
b1011010 o
b101100000 j
b101100100 )
b101100000 *
b1011010 [
1g
b1011010 (
#1400
0"
0Z
#1405
1"
1Z
b1011011 o
b101100100 j
b101101000 )
b101100100 *
b1011011 [
0g
1f
b1011011 (
#1410
0"
0Z
